ProcessingPipeline
TreeSolver
cassiopeia
