Metadata-Version: 1.1
Name: cassiopeia-lineage
Version: 1.0.4
Summary: Single Cell Lineage Reconstruction with Cas9-Enabled Lineage Recorders
Home-page: https://github.com/YosefLab/Cassiopeia
Author: UNKNOWN
Author-email: mattjones315@berkeley.edu
License: MIT license
Keywords: scLT
Platform: UNKNOWN
Classifier: Development Status :: 4 - Beta
Classifier: Intended Audience :: Science/Research
Classifier: License :: OSI Approved :: MIT License
Classifier: Programming Language :: Python :: 3
Classifier: Operating System :: MacOS :: MacOS X
Classifier: Operating System :: Microsoft :: Windows
Classifier: Operating System :: POSIX :: Linux
Classifier: Topic :: Scientific/Engineering :: Bio-Informatics
